LICENSE.txt
MANIFEST.in
README.txt
__init__.py
setup.cfg
setup.py
django_mothertongue.egg-info/PKG-INFO
django_mothertongue.egg-info/SOURCES.txt
django_mothertongue.egg-info/dependency_links.txt
django_mothertongue.egg-info/not-zip-safe
django_mothertongue.egg-info/requires.txt
django_mothertongue.egg-info/top_level.txt
docs/history.rst
docs/index.rst
docs/setup.rst
docs/usage.rst
mothertongue/__init__.py
mothertongue/context_processors.py
mothertongue/models.py
mothertongue/tests/__init__.py
mothertongue/tests/models.py
mothertongue/tests/runtests.py
mothertongue/tests/test_settings.py
mothertongue/tests/test_utils.py
mothertongue/tests/tests.py
