Metadata-Version: 1.0
Name: django-mothertongue
Version: 0.0.6
Summary: A light-weight translation application designed to simplify the process of creating multi-lingual websites and serving appropriate content.
Home-page: https://github.com/robcharlwood/django-mothertongue
Author: Rob Charlwood
Author-email: robcharlwood@gmail.com
License: MIT License
Keywords: django i18n model translation
Platform: UNKNOWN
Classifier: Development Status :: 5 - Production/Stable
Classifier: Environment :: Web Environment
Classifier: Framework :: Django
Classifier: Intended Audience :: Developers
Classifier: License :: OSI Approved :: MIT License
Classifier: Operating System :: OS Independent
Classifier: Natural Language :: English
Classifier: Programming Language :: Python
Classifier: Topic :: Software Development :: Libraries :: Application Frameworks
Classifier: Topic :: Software Development :: Libraries :: Python Modules
Classifier: Topic :: Software Development :: Localization
